{
  "metadata": {
    "id": "1_s14_14.6-0-3-4",
    "type": "prove",
    "tags": {
      "target_object": "Christoffel_symbols_transverse",
      "coordinate": "spherical_static",
      "scenario": "static_gravitational_field_weight_reduce",
      "method": "local_flat_limit",
      "generalization_axis": "limit",
      "metric": "AntiDeSitterStatic"
    },
    "tools_used": [
      "EinsteinPy",
      "judge:glm-5.1+red_team:glm-5.1"
    ],
    "validated": false,
    "source": "generated",
    "source_id": "1_s14_14.6",
    "source_type": "problem_set",
    "stage": "scale:soft_rewrite",
    "lineage": [
      "1_s14_14.6",
      "1_s14_14.6-0",
      "1_s14_14.6-0-3",
      "1_s14_14.6-0-3-4"
    ],
    "topic": null,
    "concepts": [],
    "cognitive_form": "derivation",
    "physics_env": "AntiDeSitterStatic",
    "soft_variant": "reduce",
    "training_value": null,
    "degraded": true,
    "quality": null
  },
  "physical_data": {
    "dimension": 4,
    "variables": [
      "t",
      "r",
      "theta",
      "phi"
    ],
    "target": [
      "$\\lim_{r \\to 0} \\Gamma^r_{\\theta\\theta} = -r$",
      "$\\lim_{r \\to 0} \\Gamma^r_{\\phi\\phi} = -r \\sin^2(\\theta)$"
    ],
    "metric": [
      [
        "-cosh(r)**2",
        "0",
        "0",
        "0"
      ],
      [
        "0",
        "1",
        "0",
        "0"
      ],
      [
        "0",
        "0",
        "sinh(r)**2",
        "0"
      ],
      [
        "0",
        "0",
        "0",
        "sin(theta)**2*sinh(r)**2"
      ]
    ],
    "metric_sympy": null
  },
  "origin": {
    "question": "考虑反德西特时空的静态坐标系，其度规为对角形式：$$\\mathrm{d}s^2 = -\\cos h^{2}(r) \\mathrm{d}t^2 + \\mathrm{d}r^2 + \\sin h^{2}(r) \\mathrm{d}\\theta^2 + \\sin^{2}(\\theta) \\sin h^{2}(r) \\mathrm{d}\\phi^2$$其中采用 $(-,+,+,+)$ 符号约定。在该时空中，横向角向应力对径向物理量（如重量）的影响由度规横向分量的径向导数决定，具体表现为 Christoffel 符号 $\\Gamma^r_{\\theta\\theta}$ 和 $\\Gamma^r_{\\phi\\phi}$。已知在此度规下，这两个符号的计算结果为 $\\Gamma^r_{\\theta\\theta} = -\\frac{\\sin h(2r)}{2}$ 和 $\\Gamma^r_{\\phi\\phi} = -\\frac{\\sin^2(\\theta)\\sin h(2r)}{2}$。请将上述 Christoffel 符号取局域平直极限 $r \\to 0$，推导其如何退化回到经典平直时空球坐标系下的对应结果，并写出极限后的具体表达式。",
    "answer": "对 $\\Gamma^r_{\\theta\\theta} = -\\frac{\\sin h(2r)}{2}$ 取 $r \\to 0$ 极限，利用小参数展开 $\\sin h(2r) \\approx 2r$，可得 $\\lim_{r \\to 0} \\Gamma^r_{\\theta\\theta} = -r$。对 $\\Gamma^r_{\\phi\\phi} = -\\frac{\\sin^2(\\theta)\\sin h(2r)}{2}$ 取 $r \\to 0$ 极限，同理可得 $\\lim_{r \\to 0} \\Gamma^r_{\\phi\\phi} = -r \\sin^2(\\theta)$。这正是经典平直时空球坐标系下对应的 Christoffel 符号表达式。物理上，在靠近原点的极小区域内，反德西特时空的曲率效应可忽略，时空局域退化为平直时空，几何联络也随之退化为平直时空球坐标的联络。",
    "solution": "在 $r \\to 0$ 的局域平直极限下，双曲函数作泰勒展开保留一阶项：$\\sin h(2r) \\approx 2r$。代入 $\\Gamma^r_{\\theta\\theta} = -\\frac{\\sin h(2r)}{2}$，得到 $\\lim_{r \\to 0} \\Gamma^r_{\\theta\\theta} = -\\frac{2r}{2} = -r$。代入 $\\Gamma^r_{\\phi\\phi} = -\\frac{\\sin^2(\\theta)\\sin h(2r)}{2}$，得到 $\\lim_{r \\to 0} \\Gamma^r_{\\phi\\phi} = -\\frac{\\sin^2(\\theta) 2r}{2} = -r \\sin^2(\\theta)$。这两项正是平直时空球坐标系度规 $\\mathrm{d}s^2 = -\\mathrm{d}t^2 + \\mathrm{d}r^2 + r^2 \\mathrm{d}\\theta^2 + r^2 \\sin^2(\\theta) \\mathrm{d}\\phi^2$ 的 Christoffel 符号计算结果，体现了局域极限下时空曲率消失，联络退化为纯粹坐标几何效应的过程。"
  },
  "verification": {
    "attempt": 0,
    "structural": {
      "ok": true,
      "ran": true
    },
    "metric_check": {
      "checker": "sympy_verify.antidesitterstatic_check",
      "status": "ok",
      "ran": true,
      "ricci_scalar": true
    },
    "judge": {
      "correct": false,
      "self_contained": false,
      "training_value": 0.2,
      "issue": "题目、answer 和 solution 中存在致命的符号书写错误：将双曲函数 \\cosh 和 \\sinh 错误地写成了 \\cos h 和 \\sin h。例如度规中的 \\cos h^{2}(r) 和 \\sin h^{2}(r)，以及 Christoffel 符号中的 \\sin h(2r)。在 LaTeX 中，\\sin h 会被渲染为三角正弦函数作用于变量 h (即 sin(h))，这完全改变了公式的数学与物理语义，使得度规和推导变得毫无意义（反德西特时空度规分量应为双曲函数而非三角函数与变量h的混合）。正确的写法必须是 \\cosh^2(r)、\\sinh^2(r) 和 \\sinh(2r)。此外，摘要指出 Kretschmann 标量为 \\frac{12}{\\alpha^{2}}，但题目中度规完全未出现曲率参数 \\alpha，也未说明 \\alpha=1 的简化假设，信息一致性存在瑕疵。",
      "ran": true
    },
    "red_team": {
      "survives": null,
      "ran": false,
      "flaw": "judge did not pass, red_team skipped"
    }
  }
}